ty_check/__init__.py
ty_check-0.1.0.dist-info/WHEEL
ty_check-0.1.0.dist-info/entry_points.txt
ty_check-0.1.0.dist-info/METADATA
ty_check-0.1.0.dist-info/RECORD
