Metadata-Version: 2.3
Name: ty-check
Version: 0.1.0
Summary: This project is taken to defend against confusion with `ty check`.
Author: Zanie Blue
Author-email: Zanie Blue <contact@zanie.dev>
Requires-Python: >=3.13
